FinalCode/new_pc.v
module new_pc(in_pc,jump_pc,branch_pc,jump,branch,new_pc);

  input [31:0]in_pc,jump_pc,branch_pc;
  input jump,branch;

  reg [31:0]temp_pc;

  output reg[31:0] new_pc=0;

  always@(in_pc,jump_pc,branch_pc)
  begin
    case(branch)
      0: temp_pc = in_pc;
      1: temp_pc = branch_pc;
    endcase

    case(jump)
      0: new_pc = temp_pc;
      1: new_pc = jump_pc;
    endcase
  end

endmodule

RathinIsAmazing/branch_pc.v
module branch_pc(in_pc,imm,branch_pc);

  input [31:0]in_pc;
  input [15:0]imm;
  output reg [31:0] branch_pc;

  reg [31:0] temp_pc;

  always@(imm)
  begin
    temp_pc = imm;
    temp_pc = temp_pc<<2;
  end

  always@(in_pc,temp_pc)
  begin
    branch_pc = temp_pc + in_pc;
  end

endmodule

FinalCode/jump_pc.v
module jump_pc(in_pc,jumper,jump_pc,out_pc);

  // This module takes care of the jump statements
  
  input [31:0]in_pc;
  input [25:0]jumper;
  output reg [31:0]jump_pc=0,out_pc=0;

  always@(in_pc)
  begin
    out_pc = in_pc+4;
  end

  always@(out_pc,jumper)
  begin
    jump_pc = {out_pc[31:29],jumper<<2};
  end
endmodule

FinalCode/pc.v
module pc(in_pc, out_pc);

  input [31:0]in_pc;
  reg clk = 1;
  output reg [31:0]out_pc = 0;

  always
  begin
    #5;
    clk=~clk;
    // $display("%b\n",clk);
  end

  // always begin
  //   $display("time: %t out_pc: %d in_pc: %d",$time,out_pc,in_pc);
  //   #1;
  // end

  always@(posedge clk)
  begin
    // $display("%d\n",in_pc);
    out_pc = in_pc;
  end
endmodule

RathinCode/PC/processor.v
module processor();

  wire [31:0] new_pc,temp_pc,inst,jump_pc,branch_pc,pc;
  reg [25:0] jumper;
  reg [15:0] imm;
  reg jump,branch;
  

  pc PC(
    .in_pc(new_pc),
    .out_pc(pc)
  );

  jump_pc Jump_pc(
    .in_pc(pc),
    .jumper(jumper),
    .jump_pc(jump_pc),
    .out_pc(temp_pc)
  );

  branch_pc Branch_pc(
    .in_pc(temp_pc),
    .imm(imm),
    .branch_pc(branch_pc) 
  );

  new_pc New_pc(
    .in_pc(temp_pc),
    .jump_pc(jump_pc),
    .branch_pc(branch_pc),
    .jump(jump), // I'm giving
    .branch(branch),
    .new_pc(new_pc)
  );

  initial begin
    $dumpfile("processor.vcd");
    $dumpvars(0,processor);
    $display("new pc: %b\n",new_pc);

    jump = 0; jumper = 0;
    branch = 0; imm = 0;
    #50;
    jump = 1;
    branch = 0;
    jumper = 10;

    #10;
    jump = 0;
    branch = 0;

    #10;
    branch = 1;
    imm = 12;

    #10;
    branch = 0;
    #10;
    $finish;
  end

endmodule

RathinIsAmazing/PC/processor.vcd
$date
	Sat Nov 24 15:00:38 2018
$end
$version
	Icarus Verilog
$end
$timescale
	1s
$end
$scope module processor $end
$var wire 32 ! temp_pc [31:0] $end
$var wire 32 " pc [31:0] $end
$var wire 32 # new_pc [31:0] $end
$var wire 32 $ jump_pc [31:0] $end
$var wire 32 % branch_pc [31:0] $end
$var reg 1 & branch $end
$var reg 16 ' imm [15:0] $end
$var reg 1 ( jump $end
$var reg 26 ) jumper [25:0] $end
$scope module Branch_pc $end
$var wire 16 * imm [15:0] $end
$var wire 32 + in_pc [31:0] $end
$var reg 32 , branch_pc [31:0] $end
$var reg 32 - temp_pc [31:0] $end
$upscope $end
$scope module Jump_pc $end
$var wire 26 . jumper [25:0] $end
$var wire 32 / in_pc [31:0] $end
$var reg 32 0 jump_pc [31:0] $end
$var reg 32 1 out_pc [31:0] $end
$upscope $end
$scope module New_pc $end
$var wire 1 & branch $end
$var wire 32 2 branch_pc [31:0] $end
$var wire 32 3 in_pc [31:0] $end
$var wire 1 ( jump $end
$var wire 32 4 jump_pc [31:0] $end
$var reg 32 5 new_pc [31:0] $end
$var reg 32 6 temp_pc [31:0] $end
$upscope $end
$scope module PC $end
$var wire 32 7 in_pc [31:0] $end
$var reg 1 8 clk $end
$var reg 32 9 out_pc [31:0] $end
$upscope $end
$upscope $end
$enddefinitions $end
#0
$dumpvars
b0 9
18
b100 7
b100 6
b100 5
b0 4
b100 3
b100 2
b100 1
b0 0
b0 /
b0 .
b0 -
b100 ,
b100 +
b0 *
b0 )
0(
b0 '
0&
b100 %
b0 $
b100 #
b0 "
b100 !
$end
#5
08
#10
b1000 %
b1000 ,
b1000 2
b1000 #
b1000 5
b1000 7
b1000 6
b1000 !
b1000 +
b1000 1
b1000 3
b100 "
b100 /
b100 9
18
#15
08
#20
b1100 %
b1100 ,
b1100 2
b1100 #
b1100 5
b1100 7
b1100 6
b1100 !
b1100 +
b1100 1
b1100 3
b1000 "
b1000 /
b1000 9
18
#25
08
#30
b10000 %
b10000 ,
b10000 2
b10000 #
b10000 5
b10000 7
b10000 6
b10000 !
b10000 +
b10000 1
b10000 3
b1100 "
b1100 /
b1100 9
18
#35
08
#40
b10100 %
b10100 ,
b10100 2
b10100 #
b10100 5
b10100 7
b10100 6
b10100 !
b10100 +
b10100 1
b10100 3
b10000 "
b10000 /
b10000 9
18
#45
08
#50
b11000 %
b11000 ,
b11000 2
b11000 6
b11000 !
b11000 +
b11000 1
b11000 3
b101000 #
b101000 5
b101000 7
b10100 "
b10100 /
b10100 9
b101000 $
b101000 0
b101000 4
18
b1010 )
b1010 .
1(
#55
08
#60
b101100 %
b101100 ,
b101100 2
b101100 #
b101100 5
b101100 7
b101100 6
b101100 !
b101100 +
b101100 1
b101100 3
b101000 "
b101000 /
b101000 9
18
0(
#65
08
#70
b1100000 #
b1100000 5
b1100000 7
b1100000 6
b110000 !
b110000 +
b110000 1
b110000 3
b1100000 %
b1100000 ,
b1100000 2
b101100 "
b101100 /
b101100 9
b110000 -
18
b1100 '
b1100 *
1&
#75
08
#80
b10010100 %
b10010100 ,
b10010100 2
b1100100 #
b1100100 5
b1100100 7
b1100100 6
b1100100 !
b1100100 +
b1100100 1
b1100100 3
b1100000 "
b1100000 /
b1100000 9
18
0&
#85
08
#90
b10011000 %
b10011000 ,
b10011000 2
b1101000 #
b1101000 5
b1101000 7
b1101000 6
b1101000 !
b1101000 +
b1101000 1
b1101000 3
b1100100 "
b1100100 /
b1100100 9
18
